bellhop/plot.py
bellhop/readers.py
bellhop/models.py
bellhop/_version.py
bellhop/constants.py
bellhop/__init__.py
bellhop/writers.py
bellhop/bellhop.py
bellhop/environment.py
bellhop/pyplot.py
bellhop/main.py
bellhop/plotutils.py
bellhop/compute.py
bellhop/bin/bellhop.exe
bellhop/bin/bellhop3d.exe
bellhop/.dylibs/libgfortran.5.dylib
bellhop/.dylibs/libquadmath.0.dylib
bellhop/.dylibs/libgcc_s.1.1.dylib
aubellhop-0.1.4.dist-info/RECORD
aubellhop-0.1.4.dist-info/WHEEL
aubellhop-0.1.4.dist-info/top_level.txt
aubellhop-0.1.4.dist-info/METADATA
aubellhop-0.1.4.dist-info/licenses/LICENSE
