Metadata-Version: 2.4
Name: aubellhop
Version: 0.1.4
Summary: Bellhop underwater acoustic propagation model
Author-email: Will Robertson <wspr81@gmail.com>
Maintainer-email: Will Robertson <wspr81@gmail.com>
License-Expression: GPL-3.0-or-later
Project-URL: Homepage, https://github.com/avc-adelaide/bellhoppe
Project-URL: Documentation, https://avc-adelaide.github.io/bellhoppe/
Project-URL: Repository, https://github.com/avc-adelaide/bellhoppe.git
Project-URL: Issues, https://github.com/avc-adelaide/bellhoppe/issues
Project-URL: Changelog, https://github.com/avc-adelaide/bellhoppe/blob/master/CHANGES.md
Classifier: Development Status :: 4 - Beta
Classifier: Programming Language :: Python :: 3.12
Classifier: Programming Language :: Python :: 3.13
Classifier: Programming Language :: Python :: 3.14
Requires-Python: <3.15,>=3.12
License-File: LICENSE
Requires-Dist: matplotlib
Requires-Dist: numpy
Requires-Dist: scipy
Requires-Dist: pandas
Requires-Dist: bokeh
Provides-Extra: dev
Requires-Dist: pytest; extra == "dev"
Requires-Dist: gcovr; extra == "dev"
Requires-Dist: ruff; extra == "dev"
Requires-Dist: coverage; extra == "dev"
Requires-Dist: mypy; extra == "dev"
Requires-Dist: jupyter; extra == "dev"
Requires-Dist: nbformat; extra == "dev"
Requires-Dist: sphinxcontrib-mermaid; extra == "dev"
Dynamic: license-file
